LICENSE
README.md
setup.py
thesisperu/__init__.py
thesisperu/scrapper.py
thesisperu/version.py
thesisperu.egg-info/PKG-INFO
thesisperu.egg-info/SOURCES.txt
thesisperu.egg-info/dependency_links.txt
thesisperu.egg-info/requires.txt
thesisperu.egg-info/top_level.txt