Metadata-Version: 1.0
Name: thesisperu
Version: 0.2
Summary: Descarga la metada de las tesis
Home-page: https://github.com/TJhon/tesis_peru
Author: Jhon
Author-email: fr.jhonk@gmail.com
License: UNKNOWN
Platform: UNKNOWN
